cerberedis/__init__.py
cerberedis/cerberedis.py
cerberedis-1.0.5.dist-info/LICENSE
cerberedis-1.0.5.dist-info/METADATA
cerberedis-1.0.5.dist-info/WHEEL
cerberedis-1.0.5.dist-info/top_level.txt
cerberedis-1.0.5.dist-info/RECORD
