Metadata-Version: 2.1
Name: cerberedis
Version: 1.0.5
Summary: A Cerberus powered frontend for Redis
Home-page: https://github.com/adamlwgriffiths/cerberedis/
Author: Adam Griffiths
Author-email: adam.lw.griffiths@gmail.com
License: BSD 2-Clause License
Platform: UNKNOWN
Classifier: Development Status :: 3 - Alpha
Classifier: Intended Audience :: Developers
Classifier: License :: OSI Approved :: BSD License
Classifier: Programming Language :: Python
Classifier: Topic :: Software Development :: Libraries :: Python Modules
Requires-Python: >=3.5
Requires-Dist: cerberus
Requires-Dist: redis
